evo_researcher/__init__.py
evo_researcher/autonolas/__init__.py
evo_researcher/autonolas/research.py
evo_researcher/benchmark/__init__.py
evo_researcher/benchmark/agents.py
evo_researcher/benchmark/benchmark.py
evo_researcher/benchmark/utils.py
evo_researcher/functions/__init__.py
evo_researcher/functions/create_embeddings_from_results.py
evo_researcher/functions/generate_subqueries.py
evo_researcher/functions/grade_info.py
evo_researcher/functions/prepare_report.py
evo_researcher/functions/rerank_results.py
evo_researcher/functions/rerank_subqueries.py
evo_researcher/functions/research.py
evo_researcher/functions/scrape_results.py
evo_researcher/functions/search.py
evo_researcher/functions/summarize.py
evo_researcher/functions/web_scrape.py
evo_researcher/functions/web_search.py
evo_researcher/main.py
evo_researcher/models/WebScrapeResult.py
evo_researcher/models/WebSearchResult.py
evo_researcher-0.1.10.dist-info/METADATA
evo_researcher-0.1.10.dist-info/WHEEL
evo_researcher-0.1.10.dist-info/RECORD
