Metadata-Version: 2.1
Name: evo_researcher
Version: 0.1.10
Summary: 
Author: Nestor Amesty
Author-email: nestor@polywrap.io
Requires-Python: >=3.10,<4.0
Classifier: Programming Language :: Python :: 3
Classifier: Programming Language :: Python :: 3.10
Classifier: Programming Language :: Python :: 3.11
Classifier: Programming Language :: Python :: 3.12
Requires-Dist: beautifulsoup4 (==4.12.2)
Requires-Dist: chromadb (==0.4.12)
Requires-Dist: click (==8.0.2)
Requires-Dist: google-api-python-client (==2.95.0)
Requires-Dist: langchain (==0.0.303)
Requires-Dist: markdownify (==0.11.6)
Requires-Dist: openai (==0.27.2)
Requires-Dist: pandas (==2.1.1)
Requires-Dist: pysqlite3-binary (>=0.5.2.post3,<0.6.0)
Requires-Dist: pytest (==7.2.1)
Requires-Dist: spacy (==3.7.2)
Requires-Dist: tabulate (>=0.9.0,<0.10.0)
Requires-Dist: tavily-python (>=0.3.0,<0.4.0)
Requires-Dist: tiktoken (==0.5.1)
